__init__.py
example.py
excel_manager.py
project.py
task.py
visualization.py
libreriagestor-0.0.1.dist-info/METADATA
libreriagestor-0.0.1.dist-info/WHEEL
libreriagestor-0.0.1.dist-info/licenses/LICENSE
libreriagestor-0.0.1.dist-info/RECORD
