Metadata-Version: 2.1
Name: LibreriaGestor
Version: 0.0.1
Summary: Libreria para gestioanr proyectos de equipos
Project-URL: Homepage, https://github.com/Gorkaei/LibreriaGestor
Project-URL: Bug Tracker, https://github.com/Gorkaei/LibreriaGestor/issues
Author-email: Gorka Escalante <gorka.escalante@alumnimondragon.edu>
License: MIT License
License-File: LICENSE
Classifier: License :: OSI Approved :: MIT License
Classifier: Operating System :: OS Independent
Classifier: Programming Language :: Python :: 3
Requires-Python: >=3.9
